gogs_cli/__init__.py
gogs_cli/__version__.py
gogs_cli/gogs_cli.py
gogs_cli-0.20.dist-info/licenses/LICENSE
gogs_cli-0.20.dist-info/METADATA
gogs_cli-0.20.dist-info/WHEEL
gogs_cli-0.20.dist-info/entry_points.txt
gogs_cli-0.20.dist-info/top_level.txt
gogs_cli-0.20.dist-info/RECORD
