Metadata-Version: 2.4
Name: gogs-cli
Version: 0.20
Summary: A high-performance, async command-line interface for interacting with Gogs Git repositories
Home-page: https://github.com/cumulus13/gogs_cli
Author: Hadi Cahyadi
Author-email: cumulus13@gmail.com
Project-URL: Bug Tracker, https://github.com/cumulus13/gogs_cli/issues
Project-URL: Documentation, https://github.com/cumulus13/gogs_cli#readme
Project-URL: Source Code, https://github.com/cumulus13/gogs_cli
Keywords: gogs,gitea,git,cli,async,repository,api,command-line,version-control
Classifier: Development Status :: 5 - Production/Stable
Classifier: Intended Audience :: Developers
Classifier: Topic :: Software Development :: Version Control :: Git
Classifier: Topic :: System :: Systems Administration
Classifier: Topic :: Utilities
Classifier: License :: OSI Approved :: MIT License
Classifier: Programming Language :: Python :: 3
Classifier: Programming Language :: Python :: 3.7
Classifier: Programming Language :: Python :: 3.8
Classifier: Programming Language :: Python :: 3.9
Classifier: Programming Language :: Python :: 3.10
Classifier: Programming Language :: Python :: 3.11
Classifier: Programming Language :: Python :: 3.12
Classifier: Operating System :: OS Independent
Classifier: Environment :: Console
Requires-Python: >=3.7
License-File: LICENSE
Requires-Dist: aiohttp>=3.8.0
Provides-Extra: full
Requires-Dist: rich>=13.0.0; extra == "full"
Requires-Dist: rich-argparse>=1.0.0; extra == "full"
Requires-Dist: configset>=2.0.0; extra == "full"
Requires-Dist: clipboard>=0.0.4; extra == "full"
Provides-Extra: rich
Requires-Dist: rich>=13.0.0; extra == "rich"
Requires-Dist: rich-argparse>=1.0.0; extra == "rich"
Provides-Extra: config
Requires-Dist: configset>=2.0.0; extra == "config"
Provides-Extra: clipboard
Requires-Dist: clipboard>=0.0.4; extra == "clipboard"
Dynamic: author
Dynamic: author-email
Dynamic: classifier
Dynamic: description
Dynamic: description-content-type
Dynamic: home-page
Dynamic: keywords
Dynamic: license-file
Dynamic: project-url
Dynamic: provides-extra
Dynamic: requires-dist
Dynamic: requires-python
Dynamic: summary
